py_style_flattener/__init__.py
py_style_flattener/py_style_flattener.py
py_style_flattener-0.0.3.dist-info/LICENSE
py_style_flattener-0.0.3.dist-info/METADATA
py_style_flattener-0.0.3.dist-info/WHEEL
py_style_flattener-0.0.3.dist-info/entry_points.txt
py_style_flattener-0.0.3.dist-info/top_level.txt
py_style_flattener-0.0.3.dist-info/RECORD
