Metadata-Version: 2.1
Name: py-style-flattener
Version: 0.0.3
Summary: Manipulate HTML by moving <style> to style=".
Home-page: https://github.com/CastixGitHub/py_style_flattener
Author: castix
Author-email: castix@autistici.org
Project-URL: Bug Reports, https://github.com/CastixGitHub/py_style_flattener/issues
Project-URL: Source, https://github.com/CastixGitHub/py_style_flattener
Keywords: html,style,css,parser,regex
Classifier: Programming Language :: Python :: 3
Classifier: License :: OSI Approved :: GNU General Public License v3 or later (GPLv3+)
Classifier: Operating System :: OS Independent
Requires-Python: >=3.6
License-File: LICENSE
Requires-Dist: pyquery (>=1.4.3)
Requires-Dist: regex (>=2022.7.25)
Provides-Extra: testing
Requires-Dist: pytest ; extra == 'testing'
Requires-Dist: pytest-cov ; extra == 'testing'
Requires-Dist: pytest-randomly ; extra == 'testing'
Requires-Dist: flake8 ; extra == 'testing'
